magic_case/__init__.py
magic_case/base.py
magic_case/camel.py
magic_case/camel_snake.py
magic_case/dot.py
magic_case/flat.py
magic_case/http_header.py
magic_case/hungarian.py
magic_case/kebab.py
magic_case/macro.py
magic_case/pascal.py
magic_case/pascal_snake.py
magic_case/path.py
magic_case/sentence.py
magic_case/slash_title.py
magic_case/snake.py
magic_case/space.py
magic_case/title.py
magic_case/upper.py
magic_case-0.3.2.dist-info/METADATA
magic_case-0.3.2.dist-info/WHEEL
magic_case-0.3.2.dist-info/licenses/LICENSE
magic_case-0.3.2.dist-info/RECORD
