Metadata-Version: 2.4
Name: magic-case
Version: 0.3.2
Summary: Lightweight utilities for converting strings between common cases
Project-URL: Homepage, https://pypi.org/project/magic-case/
Project-URL: Repository, https://github.com/your-org/magic-case
Author-email: Shubhro Shekhar <shubhroshekhar@gmail.com>
License: MIT
License-File: LICENSE
Requires-Python: >=3.9
